[
  {
    "name": "__cf_bm",
    "value": "TG1b5jaJB_pZaKTMaxaSobvl3jhan0kPew1HR7mHpNs-1762307379.9487493-1.0.1.1-dTklU6B.1igkYl.iUfTn3lsQ4s4GpN2zNvnp4k6mon.Cm_e524rR8cawzW63TvDTVtpgUnhu_.YwRkNp1vAEoA7sA11SayHSNC7Sbg0n.4p1DIYYpw2CyPJ77Fpz9Zc7",
    "domain": ".x.com",
    "path": "/",
    "expires": 1762309181.519415,
    "size": 206,
    "httpOnly": true,
    "secure": true,
    "session": false,
    "priority": "Medium",
    "sameParty": false,
    "sourceScheme": "Secure"
  },
  {
    "name": "twid",
    "value": "u%3D1985185987056824320",
    "domain": ".x.com",
    "path": "/",
    "expires": 1793843374.497959,
    "size": 27,
    "httpOnly": false,
    "secure": true,
    "session": false,
    "sameSite": "None",
    "priority": "Medium",
    "sameParty": false,
    "sourceScheme": "Secure"
  },
  {
    "name": "lang",
    "value": "en",
    "domain": "x.com",
    "path": "/",
    "expires": -1,
    "size": 6,
    "httpOnly": false,
    "secure": false,
    "session": true,
    "priority": "Medium",
    "sameParty": false,
    "sourceScheme": "Secure"
  },
  {
    "name": "gt",
    "value": "1985886844396192033",
    "domain": ".x.com",
    "path": "/",
    "expires": 1762316296.117728,
    "size": 21,
    "httpOnly": false,
    "secure": true,
    "session": false,
    "priority": "Medium",
    "sameParty": false,
    "sourceScheme": "Secure"
  },
  {
    "name": "ct0",
    "value": "31ce17acd0b5c8d4cfdca680368bdd5aea227b5aeb0159ce03e3b72636714e9436b747e330c5c8abd3cdd3d2bdaf57087edbbc096a34851c0426a9ac32213fcc8c7b5ae974743f2cf7ea339d4296d34d",
    "domain": ".x.com",
    "path": "/",
    "expires": 1796867370.748438,
    "size": 163,
    "httpOnly": false,
    "secure": true,
    "session": false,
    "sameSite": "Lax",
    "priority": "Medium",
    "sameParty": false,
    "sourceScheme": "Secure"
  },
  {
    "name": "__cuid",
    "value": "d3cbc15461564de98a9683f075879941",
    "domain": ".x.com",
    "path": "/",
    "expires": 1796867372,
    "size": 38,
    "httpOnly": false,
    "secure": false,
    "session": false,
    "sameSite": "Lax",
    "priority": "Medium",
    "sameParty": false,
    "sourceScheme": "Secure"
  },
  {
    "name": "att",
    "value": "1-NOuZ2c1CYpTf1eMEnC77JuEziM16PDfzKBg05hV1",
    "domain": ".x.com",
    "path": "/",
    "expires": 1762393771.23371,
    "size": 45,
    "httpOnly": true,
    "secure": true,
    "session": false,
    "sameSite": "None",
    "priority": "Medium",
    "sameParty": false,
    "sourceScheme": "Secure"
  },
  {
    "name": "auth_token",
    "value": "2dc6116f470dd6758309d4fd5d520270881d6fca",
    "domain": ".x.com",
    "path": "/",
    "expires": 1796867370.337287,
    "size": 50,
    "httpOnly": true,
    "secure": true,
    "session": false,
    "sameSite": "None",
    "priority": "Medium",
    "sameParty": false,
    "sourceScheme": "Secure"
  },
  {
    "name": "personalization_id",
    "value": "\"v1_2STywsEZNk0Q2WhjRyUI7Q==\"",
    "domain": ".x.com",
    "path": "/",
    "expires": 1796867296.117682,
    "size": 47,
    "httpOnly": false,
    "secure": true,
    "session": false,
    "sameSite": "None",
    "priority": "Medium",
    "sameParty": false,
    "sourceScheme": "Secure"
  },
  {
    "name": "g_state",
    "value": "{\"i_l\":0,\"i_ll\":1762307322132}",
    "domain": "x.com",
    "path": "/",
    "expires": 1777859368,
    "size": 37,
    "httpOnly": false,
    "secure": false,
    "session": false,
    "priority": "Medium",
    "sameParty": false,
    "sourceScheme": "Secure"
  },
  {
    "name": "guest_id",
    "value": "v1%3A176230729433413153",
    "domain": ".x.com",
    "path": "/",
    "expires": 1796867295.790554,
    "size": 31,
    "httpOnly": false,
    "secure": true,
    "session": false,
    "sameSite": "None",
    "priority": "Medium",
    "sameParty": false,
    "sourceScheme": "Secure"
  },
  {
    "name": "guest_id_marketing",
    "value": "v1%3A176230729433413153",
    "domain": ".x.com",
    "path": "/",
    "expires": 1796867374.497924,
    "size": 41,
    "httpOnly": false,
    "secure": true,
    "session": false,
    "sameSite": "None",
    "priority": "Medium",
    "sameParty": false,
    "sourceScheme": "Secure"
  },
  {
    "name": "guest_id_ads",
    "value": "v1%3A176230729433413153",
    "domain": ".x.com",
    "path": "/",
    "expires": 1796867374.497822,
    "size": 35,
    "httpOnly": false,
    "secure": true,
    "session": false,
    "sameSite": "None",
    "priority": "Medium",
    "sameParty": false,
    "sourceScheme": "Secure"
  },
  {
    "name": "kdt",
    "value": "50LA0gLc8IzG6pSjdgDtylJY2Ducm69JC04PCFes",
    "domain": ".x.com",
    "path": "/",
    "expires": 1796867370.337151,
    "size": 43,
    "httpOnly": true,
    "secure": true,
    "session": false,
    "priority": "Medium",
    "sameParty": false,
    "sourceScheme": "Secure"
  }
]